pyb_d/__init__.py
pyb_d/__main__.py
pyb_d/cli.py
pyb_assistent-0.1.3.dist-info/METADATA
pyb_assistent-0.1.3.dist-info/WHEEL
pyb_assistent-0.1.3.dist-info/entry_points.txt
pyb_assistent-0.1.3.dist-info/top_level.txt
pyb_assistent-0.1.3.dist-info/RECORD
