Metadata-Version: 2.4
Name: pyb-assistent
Version: 0.1.3
Summary: PyB PyPi build assist
Author: xqrto
Classifier: Programming Language :: Python :: 3
Classifier: License :: OSI Approved :: MIT License
Classifier: Operating System :: OS Independent
Requires-Python: >=3.7
Dynamic: author
Dynamic: classifier
Dynamic: description
Dynamic: description-content-type
Dynamic: requires-python
Dynamic: summary
